shoki/__init__.py
shoki/cli.py
shoki/datacore.py
shoki/formatter.py
shoki/parsing.py
shoki/shoki_config.py
shoki/templates/webcompatwiki/intro.tmpl
shoki/templates/webcompatwiki/intro_no_chat.tmpl
shoki/templates/webcompatwiki/main.tmpl
shoki/templates/webcompatwiki/todo.tmpl
shoki/templates/webcompatwiki/topic.tmpl
shoki/templates/webcompatwiki/voice.tmpl
shoki-2.0.2.dist-info/LICENSE
shoki-2.0.2.dist-info/METADATA
shoki-2.0.2.dist-info/WHEEL
shoki-2.0.2.dist-info/entry_points.txt
shoki-2.0.2.dist-info/top_level.txt
shoki-2.0.2.dist-info/RECORD
