Metadata-Version: 2.1
Name: shoki
Version: 2.0.2
Summary: Generate minutes from a text file
Home-page: https://github.com/karlcow/shoki
Author: Karl Dubost
Author-email: karl+shoki@la-grange.net
License: MPL
Platform: UNKNOWN
Classifier: License :: OSI Approved :: Mozilla Public License 2.0 (MPL 2.0)
Classifier: Natural Language :: English
Classifier: Programming Language :: Python :: 3
Classifier: Programming Language :: Python :: 3.7
